invenio_global_search/__init__.py
invenio_global_search/cli.py
invenio_global_search/components.py
invenio_global_search/config.py
invenio_global_search/ext.py
invenio_global_search/proxies.py
invenio_global_search/serializers.py
invenio_global_search-0.3.0.dist-info/licenses/AUTHORS.rst
invenio_global_search-0.3.0.dist-info/licenses/LICENSE
tests/__init__.py
tests/conftest.py
invenio_global_search-0.3.0.dist-info/METADATA
invenio_global_search-0.3.0.dist-info/WHEEL
invenio_global_search-0.3.0.dist-info/entry_points.txt
invenio_global_search-0.3.0.dist-info/top_level.txt
invenio_global_search-0.3.0.dist-info/RECORD
