Metadata-Version: 2.4
Name: invenio-global-search
Version: 0.3.0
Summary: InvenioRDM module for a Global Search
Home-page: https://github.com/tu-graz-library/invenio-global-search
Author: TU Graz
Author-email: 
License: MIT
Keywords: invenio rdm search
Platform: any
Classifier: Programming Language :: Python :: 3.12
Classifier: Development Status :: 5 - Production/Stable
Classifier: License :: OSI Approved :: MIT License
Classifier: Operating System :: OS Independent
Classifier: Programming Language :: Python
Classifier: Topic :: Software Development :: Libraries :: Python Modules
Requires-Python: >=3.12
License-File: LICENSE
License-File: AUTHORS.rst
Requires-Dist: invenio-records-global-search>=0.0.1
Provides-Extra: rdm
Requires-Dist: invenio-rdm-records>=18.0.0; extra == "rdm"
Provides-Extra: lom
Requires-Dist: invenio-records-lom>=0.12.0; extra == "lom"
Provides-Extra: marc21
Requires-Dist: invenio-records-marc21>=0.17.0; extra == "marc21"
Provides-Extra: tests
Requires-Dist: invenio-app>=2.0.0; extra == "tests"
Requires-Dist: invenio-search[opensearch2]>=3.0.0; extra == "tests"
Requires-Dist: pytest-black-ng>=0.4.0; extra == "tests"
Requires-Dist: pytest-invenio>=3.0.0; extra == "tests"
Requires-Dist: ruff>=0.11.9; extra == "tests"
Requires-Dist: ty>=0.0.0a1; extra == "tests"
Requires-Dist: sphinx>=4.5.0; extra == "tests"
Dynamic: license-file
